Metadata-Version: 1.0
Name: utilThreading
Version: 1.0.0
Summary: A collection of classes which execute common tasks that require execution on an additional threads.
Home-page: https://github.com/seanwiseman/util-threading
Author: Sean Wiseman
Author-email: seanwiseman2012@gmail.com
License: MIT
Platform: UNKNOWN
